CHANGES.rst
CONTRIBUTORS.rst
DEVELOP.rst
LICENSE.rst
MANIFEST.in
README.rst
setup.cfg
setup.py
docs/index.rst
src/collective/__init__.py
src/collective.siteimprove.egg-info/PKG-INFO
src/collective.siteimprove.egg-info/SOURCES.txt
src/collective.siteimprove.egg-info/dependency_links.txt
src/collective.siteimprove.egg-info/entry_points.txt
src/collective.siteimprove.egg-info/namespace_packages.txt
src/collective.siteimprove.egg-info/not-zip-safe
src/collective.siteimprove.egg-info/requires.txt
src/collective.siteimprove.egg-info/top_level.txt
src/collective/siteimprove/__init__.py
src/collective/siteimprove/configure.zcml
src/collective/siteimprove/interfaces.py
src/collective/siteimprove/permissions.zcml
src/collective/siteimprove/profile.zcml
src/collective/siteimprove/setuphandlers.py
src/collective/siteimprove/testing.py
src/collective/siteimprove/browser/__init__.py
src/collective/siteimprove/browser/configure.zcml
src/collective/siteimprove/browser/controlpanel.py
src/collective/siteimprove/browser/events.py
src/collective/siteimprove/browser/siteimprove-head.pt
src/collective/siteimprove/browser/utils.py
src/collective/siteimprove/browser/viewlets.py
src/collective/siteimprove/browser/static/.gitkeep
src/collective/siteimprove/browser/static/siteimprove-compiled.js
src/collective/siteimprove/browser/static/siteimprove-compiled.js.map
src/collective/siteimprove/browser/static/siteimprove.js
src/collective/siteimprove/locales/collective.siteimprove.pot
src/collective/siteimprove/locales/update.sh
src/collective/siteimprove/profiles/default/actions.xml
src/collective/siteimprove/profiles/default/browserlayer.xml
src/collective/siteimprove/profiles/default/controlpanel.xml
src/collective/siteimprove/profiles/default/metadata.xml
src/collective/siteimprove/profiles/default/registry.xml
src/collective/siteimprove/profiles/default/rolemap.xml
src/collective/siteimprove/profiles/uninstall/actions.xml
src/collective/siteimprove/profiles/uninstall/browserlayer.xml
src/collective/siteimprove/profiles/uninstall/controlpanel.xml
src/collective/siteimprove/profiles/uninstall/registry.xml
src/collective/siteimprove/tests/__init__.py
src/collective/siteimprove/tests/test_robot.py
src/collective/siteimprove/tests/test_setup.py
src/collective/siteimprove/tests/robot/test_example.robot